<InsertObservation xmlns="http://www.opengis.net/sos/2.0" version="2.0.0" service="SOS">
  <ns:extension xmlns:ns="http://www.opengis.net/swes/2.0">
    <swe:Boolean xmlns:swe="http://www.opengis.net/swe/2.0" definition="SplitDataArrayIntoObservations">
      <swe:value>true</swe:value>
    </swe:Boolean>
  </ns:extension>
  <offering>{__offeringUri__}</offering>
  <observation>
    <ns:OM_Observation xmlns:ns="http://www.opengis.net/om/2.0" xmlns:ns1="http://www.opengis.net/gml/3.2" ns1:id="observation">
      <ns:type xmlns:xlin="http://www.w3.org/1999/xlink" xlin:href="http://www.opengis.net/def/observationType/OGC-OM/2.0/OM_SWEArrayObservation"/>
      <ns:phenomenonTime>
        <ns1:TimePeriod ns1:id="phenomenonTime">
          <ns1:beginPosition>{__phenomenonStartTime__}</ns1:beginPosition>
          <ns1:endPosition>{__phenomenonEndTime__}</ns1:endPosition>
        </ns1:TimePeriod>
      </ns:phenomenonTime>
      <ns:resultTime>
        <ns1:TimeInstant ns1:id="resultTime">
          <ns1:timePosition>{__resultTime__}</ns1:timePosition>
        </ns1:TimeInstant>
      </ns:resultTime>
      <ns:procedure xmlns:xlin="http://www.w3.org/1999/xlink" xlin:href="{__procedureUniqueId__}"/>
      <ns:observedProperty xmlns:xlin="http://www.w3.org/1999/xlink" xlin:href="{__observablePropertyName__}"/>
      <ns:featureOfInterest xmlns:xlin="http://www.w3.org/1999/xlink" xlin:href="{__featureOfInterestId__}"/>
      <ns2:result xmlns:ns="http://www.opengis.net/swe/2.0" xmlns:ns2="http://www.opengis.net/om/2.0" xmlns:xsi="http://www.w3.org/2001/XMLSchema-instance" xsi:type="ns:DataArrayPropertyType">
        <ns:DataArray>
          <ns:elementCount>
            <ns:Count>
              <ns:value>{__pointCount__}</ns:value>
            </ns:Count>
          </ns:elementCount>
          <ns:elementType name="definition">
            <ns:DataRecord>
              <ns:field name="phenomenonTime">
                <ns:Time definition="http://www.opengis.net/def/property/OGC/0/PhenomenonTime">
                  <ns:uom xmlns:xlin="http://www.w3.org/1999/xlink" xlin:href="http://www.opengis.net/def/uom/ISO-8601/0/Gregorian"/>
                </ns:Time>
              </ns:field>
              <ns:field name="{__observablePropertyFieldName__}">
                <ns:Quantity definition="{__observablePropertyName__}">
                  <ns:uom code="{__observablePropertyUnit__}"/>
                </ns:Quantity>
              </ns:field>
            </ns:DataRecord>
          </ns:elementType>
          <ns:encoding>
            <ns:TextEncoding tokenSeparator="{__pointTokenSeparator__}" blockSeparator="{__pointBlockSeparator__}"/>
          </ns:encoding>
          <ns:values>{__pointValues__}</ns:values>
        </ns:DataArray>
      </ns2:result>
    </ns:OM_Observation>
  </observation>
</InsertObservation>